dyf/__init__.py
dyf/classifier.py
dyf/io.py
dyf-0.4.0.dist-info/METADATA
dyf-0.4.0.dist-info/WHEEL
dyf-0.4.0.dist-info/top_level.txt
dyf-0.4.0.dist-info/RECORD
