Metadata-Version: 2.4
Name: dyf
Version: 0.4.0
Summary: Density Yields Features - discover structure in embedding spaces
Author-email: Justin Donaldson <jdonaldson@gmail.com>
License: MIT
Project-URL: Homepage, https://github.com/jdonaldson/dyf
Project-URL: Repository, https://github.com/jdonaldson/dyf
Project-URL: Issues, https://github.com/jdonaldson/dyf/issues
Keywords: outlier,classification,lsh,pca,embeddings,machine-learning
Classifier: Development Status :: 4 - Beta
Classifier: Intended Audience :: Developers
Classifier: Intended Audience :: Science/Research
Classifier: License :: OSI Approved :: MIT License
Classifier: Programming Language :: Python :: 3
Classifier: Programming Language :: Python :: 3.9
Classifier: Programming Language :: Python :: 3.10
Classifier: Programming Language :: Python :: 3.11
Classifier: Programming Language :: Python :: 3.12
Classifier: Topic :: Scientific/Engineering :: Artificial Intelligence
Requires-Python: >=3.9
Requires-Dist: numpy>=1.20
Requires-Dist: dyf-rs>=0.4.0
Provides-Extra: dev
Requires-Dist: pytest>=7.0; extra == "dev"
Requires-Dist: pyarrow>=10.0; extra == "dev"
Provides-Extra: full
Requires-Dist: pyarrow>=10.0; extra == "full"
Requires-Dist: polars>=0.19; extra == "full"
Requires-Dist: scikit-learn>=1.0; extra == "full"
Requires-Dist: sentence-transformers>=2.2; extra == "full"
Requires-Dist: openai>=1.0; extra == "full"
Provides-Extra: io
Requires-Dist: safetensors>=0.4; extra == "io"
